{
  "actors": [
    {
      "type": "Actor",
      "name": "TitleMusic",
      "active": true,
      "components": [
        {
          "type": "AudioComponent",
          "sound_name": "Audio/Music/TitleMusic.mp3",
          "loop": true,
          "play_on_start": true
        }
      ]
    },
    {
      "type": "Actor",
      "name": "bgCobble",
      "transform": {
        "position": [
          960,
          540
        ],
        "scale": [
          3,
          3
        ],
        "rotation": 0
      },
      "components": [
        {
          "type": "SpriteComponent",
          "texture_name": "Images/cobble.jpg"
        }
      ]
    },
    {
      "type": "Actor",
      "name": "bgScroll",
      "transform": {
        "position": [
          960,
          540
        ],
        "scale": [
          1,
          1
        ],
        "rotation": 0
      },
      "components": [
        {
          "type": "SpriteComponent",
          "texture_name": "Images/scroll.png"
        }
      ]
    },
    {
      "type": "Actor",
      "name": "StartText",
      "tag": "Clickable",
      "active": true,
      "transform": {
        "position": [
          780,
          340
        ],
        "scale": [
          3.5,
          3.5
        ],
        "rotation": 0
      },
      "components": [
        {
          "type": "SpriteComponent",
          "texture_name": "Images/start.png"
        },
        {
          "type": "RBPhysicsComponent",
          "damping": 0.4,
          "data.gravity_scale": 0,
          "data.constrain_angle": true
        },
        {
          "type": "CollisionComponent",
          "data.restitution": 0.7,
          "data.is_trigger": true,
          "data.size": [
            100,
            100
          ]
        }
      ]
    },
    {
      "type": "Actor",
      "name": "ExitText",
      "tag": "Clickable",
      "active": true,
      "transform": {
        "position": [
          780,
          540
        ],
        "scale": [
          3.5,
          3.5
        ],
        "rotation": 0
      },
      "components": [
        {
          "type": "TextComponent",
          "text": "Quit Game",
          "font_name": "Fonts/Enchanted.ttf",
          "font_size": 32,
          "registration": [
            0.0,
            0.5
          ],
          "color": [
            0,
            0,
            0,
            255
          ]
        },
        {
          "type": "RBPhysicsComponent",
          "data.gravity_scale": 0,
          "data.constrain_angle": true,
          "data.is_dynamic": false
        },
        {
          "type": "CollisionComponent",
          "data.is_trigger": true,
          "data.size": [
            100,
            100
          ]
        }
      ]
    },
    {
      "type": "Actor",
      "name": "CreditsText",
      "active": true,
      "transform": {
        "position": [
          770,
          865
        ],
        "scale": [
          1.5,
          1.5
        ],
        "rotation": 0
      },
      "components": [
        {
          "type": "TextComponent",
          "text": "Made By Collin, Platte, Ryan",
          "font_name": "Fonts/Enchanted.ttf",
          "font_size": 16,
          "registration": [
            0.0,
            0.5
          ],
          "color": [
            0,
            0,
            0,
            255
          ]
        }
      ]
    },
    {
      "type": "Actor",
      "name": "Mouse",
      "transform": {
        "scale": [
          1,
          1
        ],
        "rotation": 0
      },
      "components": [
        {
          "type": "RBPhysicsComponent",
          "damping": 0.4,
          "data.gravity_scale": 0,
          "data.constrain_angle": true
        },
        {
          "type": "EnemyComponent",
          "speed": 20,
          "health": 30,
          "damage": 10
        },
        {
          "type": "CollisionComponent",
          "data.restitution": 0.7,
          "scale_offset": [
            0.3,
            0.5
          ],
          "data.is_trigger": true,
          "data.size": [
            20,
            23
          ]
        },
        {
          "type": "MouseComponent"
        }

      ]
    }
  ]
}